cellocity/__init__.py
cellocity/analysis.py
cellocity/channel.py
cellocity/validation.py
cellocity-1.0.0.dist-info/LICENSE
cellocity-1.0.0.dist-info/METADATA
cellocity-1.0.0.dist-info/WHEEL
cellocity-1.0.0.dist-info/top_level.txt
cellocity-1.0.0.dist-info/RECORD
