Metadata-Version: 2.1
Name: cellocity
Version: 1.0.0
Summary: Velocity and vector analysis of microscopy data
Home-page: https://github.com/oftatkofta/cellocity
Author: Jens Eriksson
Author-email: jens.eriksson@imbim.uu.se
License: GPLv3
Project-URL: Documentation, https://cellocity.readthedocs.io/en/latest/
Project-URL: Research group, https://www.imbim.uu.se/research-groups/infection-and-defence/sellin-mikael/
Project-URL: Source, https://github.com/oftatkofta/cellocity
Platform: UNKNOWN
Classifier: Programming Language :: Python :: 3
Classifier: License :: OSI Approved :: GNU General Public License v3 (GPLv3)
Classifier: Operating System :: OS Independent
Classifier: Development Status :: 4 - Beta
Classifier: Topic :: Scientific/Engineering
Requires-Python: >=3.6
Requires-Dist: docutils (>=0.16)
Requires-Dist: tifffile (==2020.2.16)
Requires-Dist: opencv-python (>4.2.0)
Requires-Dist: cython (>=0.29.19)
Requires-Dist: OpenPIV (==0.22.2)
Requires-Dist: numpy (>=1.18.1)
Requires-Dist: pandas (>=1.0.1)
Requires-Dist: matplotlib (>=3.2.1)
Requires-Dist: seaborn (>=0.10.1)
Requires-Dist: sphinxcontrib-bibtex (==1.0.0)
